mlmachine/__init__.py
mlmachine/data.py
mlmachine/machine.py
mlmachine/datasets/__init__.py
mlmachine/datasets/attrition/__init__.py
mlmachine/datasets/attrition/data.pkl
mlmachine/datasets/housing/__init__.py
mlmachine/datasets/housing/test.pkl
mlmachine/datasets/housing/train.pkl
mlmachine/datasets/titanic/__init__.py
mlmachine/datasets/titanic/test.pkl
mlmachine/datasets/titanic/train.pkl
mlmachine/explore/__init__.py
mlmachine/explore/eda_preprocessing.py
mlmachine/explore/eda_suite.py
mlmachine/features/__init__.py
mlmachine/features/outlier.py
mlmachine/features/preprocessing.py
mlmachine/features/selection.py
mlmachine/model/__init__.py
mlmachine/model/evaluate/__init__.py
mlmachine/model/evaluate/summarize.py
mlmachine/model/evaluate/visualize.py
mlmachine/model/explain/__init__.py
mlmachine/model/explain/visualize.py
mlmachine/model/tune/__init__.py
mlmachine/model/tune/bayesian_optim_search.py
mlmachine/model/tune/power_grid_search.py
mlmachine/model/tune/stack.py
mlmachine-0.1.5.dist-info/LICENSE
mlmachine-0.1.5.dist-info/METADATA
mlmachine-0.1.5.dist-info/WHEEL
mlmachine-0.1.5.dist-info/top_level.txt
mlmachine-0.1.5.dist-info/RECORD
